{
  "actions": [],
  "allow_import": 1,
  "allow_rename": 1,
  "autoname": "field:zone_code",
  "doctype": "DocType",
  "engine": "InnoDB",
  "field_order": [
    "header_section",
    "zone_code",
    "zone_name",
    "depot",
    "block",
    "category",
    "is_active",
    "column_break_1",
    "capacity",
    "max_rows",
    "max_rows_full",
    "max_tiers",
    "notes"
  ],
  "fields": [
    {
      "fieldname": "header_section",
      "fieldtype": "Section Break",
      "label": "Yard Zone"
    },
    {
      "bold": 1,
      "description": "Stable code = document name. SOP zones use codes like OAK1-KIRI-DIRTY; legacy zones keep their original names (Storage_Yard_A, ...).",
      "fieldname": "zone_code",
      "fieldtype": "Data",
      "label": "Zone Code",
      "reqd": 1,
      "unique": 1
    },
    {
      "fieldname": "zone_name",
      "fieldtype": "Data",
      "in_list_view": 1,
      "label": "Zone Name",
      "reqd": 1
    },
    {
      "description": "Depot this zone physically belongs to.",
      "fieldname": "depot",
      "fieldtype": "Link",
      "in_list_view": 1,
      "in_standard_filter": 1,
      "label": "Depot",
      "options": "Depot",
      "reqd": 1
    },
    {
      "description": "Physical block within the depot (SOP: Blok Kiri / Blok Kanan). Leave blank for standalone zones (cleaning bay, workshop, survey).",
      "fieldname": "block",
      "fieldtype": "Select",
      "in_standard_filter": 1,
      "label": "Block",
      "options": "\nBlok Kiri\nBlok Kanan"
    },
    {
      "description": "Functional category — drives the status-based placement recommendation.",
      "fieldname": "category",
      "fieldtype": "Select",
      "in_list_view": 1,
      "in_standard_filter": 1,
      "label": "Category",
      "options": "Empty Dirty Queue\nCleaning Bay\nReady\nEmpty Clean\nWorkshop\nSurvey\nGate",
      "reqd": 1
    },
    {
      "default": "1",
      "fieldname": "is_active",
      "fieldtype": "Check",
      "in_list_view": 1,
      "in_standard_filter": 1,
      "label": "Active"
    },
    {
      "fieldname": "column_break_1",
      "fieldtype": "Column Break"
    },
    {
      "default": "0",
      "description": "Total slot capacity used for the occupancy / utilisation view.",
      "fieldname": "capacity",
      "fieldtype": "Int",
      "in_list_view": 1,
      "label": "Capacity (slots)"
    },
    {
      "default": "5",
      "description": "SOP standard horizontal limit (rows).",
      "fieldname": "max_rows",
      "fieldtype": "Int",
      "label": "Max Rows (normal)"
    },
    {
      "default": "6",
      "description": "SOP tolerance when the depot is full.",
      "fieldname": "max_rows_full",
      "fieldtype": "Int",
      "label": "Max Rows (full)"
    },
    {
      "default": "5",
      "description": "SOP vertical stacking limit (tiers).",
      "fieldname": "max_tiers",
      "fieldtype": "Int",
      "label": "Max Tiers"
    },
    {
      "fieldname": "notes",
      "fieldtype": "Small Text",
      "label": "Notes"
    }
  ],
  "links": [],
  "modified": "2026-06-12",
  "module": "Operations",
  "name": "Yard Zone",
  "search_fields": "zone_name, depot, category",
  "sort_field": "zone_code",
  "sort_order": "ASC",
  "title_field": "zone_name"
}
